ablog/__init__.py
ablog/_version.py
ablog/blog.py
ablog/commands.py
ablog/conf.py
ablog/post.py
ablog/start.py
ablog/version.py
ablog/locales/ca/LC_MESSAGES/sphinx.mo
ablog/locales/ca/LC_MESSAGES/sphinx.po
ablog/locales/de/LC_MESSAGES/sphinx.mo
ablog/locales/de/LC_MESSAGES/sphinx.po
ablog/locales/es/LC_MESSAGES/sphinx.mo
ablog/locales/es/LC_MESSAGES/sphinx.po
ablog/locales/et/LC_MESSAGES/sphinx.mo
ablog/locales/et/LC_MESSAGES/sphinx.po
ablog/locales/fr/LC_MESSAGES/sphinx.mo
ablog/locales/fr/LC_MESSAGES/sphinx.po
ablog/locales/ru/LC_MESSAGES/sphinx.mo
ablog/locales/ru/LC_MESSAGES/sphinx.po
ablog/locales/tr/LC_MESSAGES/sphinx.mo
ablog/locales/tr/LC_MESSAGES/sphinx.po
ablog/locales/zh_CN/LC_MESSAGES/sphinx.mo
ablog/locales/zh_CN/LC_MESSAGES/sphinx.po
ablog/templates/archives.html
ablog/templates/authors.html
ablog/templates/catalog.html
ablog/templates/categories.html
ablog/templates/collection.html
ablog/templates/languages.html
ablog/templates/locations.html
ablog/templates/page.html
ablog/templates/postcard.html
ablog/templates/postcard2.html
ablog/templates/postnavy.html
ablog/templates/recentposts.html
ablog/templates/redirect.html
ablog/templates/tagcloud.html
tests/__init__.py
tests/conftest.py
tests/test_build.py
tests/test_postlist.py
tests/roots/test-build/conf.py
tests/roots/test-build/foo-empty-post.rst
tests/roots/test-build/index.rst
tests/roots/test-build/post.rst
tests/roots/test-postlist/conf.py
tests/roots/test-postlist/index.rst
tests/roots/test-postlist/post.rst
tests/roots/test-postlist/postlist.rst
photon_ablog-0.1.0.dist-info/LICENSE
photon_ablog-0.1.0.dist-info/METADATA
photon_ablog-0.1.0.dist-info/WHEEL
photon_ablog-0.1.0.dist-info/entry_points.txt
photon_ablog-0.1.0.dist-info/top_level.txt
photon_ablog-0.1.0.dist-info/RECORD
